{
  "resource_state": 3,
  "athlete": {
    "id": 12778566,
    "resource_state": 1
  },
  "name": "Visite de Paris Village Nature",
  "distance": 1000.0,
  "moving_time": 3600,
  "elapsed_time": 3600,
  "total_elevation_gain": 0.0,
  "type": "Walk",
  "sport_type": "Walk",
  "workout_type": null,
  "device_name": "Strava App",
  "id": 18447442141,
  "start_date": "2026-05-09T10:00:00Z",
  "start_date_local": "2026-05-09T12:00:00Z",
  "timezone": "(GMT+01:00) Europe/Paris",
  "utc_offset": 7200,
  "location_city": null,
  "location_state": null,
  "location_country": null,
  "achievement_count": 0,
  "kudos_count": 0,
  "comment_count": 0,
  "athlete_count": 1,
  "photo_count": 0,
  "map": {
    "id": "a18447442141",
    "polyline": null,
    "resource_state": 3,
    "summary_polyline": null
  },
  "trainer": false,
  "commute": false,
  "manual": false,
  "private": false,
  "visibility": "everyone",
  "flagged": false,
  "gear_id": null,
  "start_latlng": [],
  "end_latlng": [],
  "average_speed": 0.278,
  "max_speed": 0.0,
  "has_heartrate": false,
  "heartrate_opt_out": false,
  "display_hide_heartrate_option": false,
  "elev_high": null,
  "elev_low": null,
  "upload_id": null,
  "upload_id_str": null,
  "external_id": null,
  "from_accepted_tag": false,
  "pr_count": 0,
  "total_photo_count": 0,
  "has_kudoed": false,
  "description": "",
  "calories": 96,
  "perceived_exertion": null,
  "prefer_perceived_exertion": null,
  "segment_efforts": [],
  "splits_metric": [],
  "splits_standard": [],
  "laps": [],
  "best_efforts": [],
  "photos": {
    "primary": null,
    "use_primary_photo": false,
    "count": 0
  },
  "stats_visibility": [],
  "hide_from_home": false,
  "embed_token": null,
  "private_note": null,
  "similar_activities": {},
  "available_zones": []
}